README.md
setup.py
NODE_deconvolution_scipy/NODE_scipy.py
NODE_deconvolution_scipy/__init__.py
NODE_deconvolution_scipy.egg-info/PKG-INFO
NODE_deconvolution_scipy.egg-info/SOURCES.txt
NODE_deconvolution_scipy.egg-info/dependency_links.txt
NODE_deconvolution_scipy.egg-info/requires.txt
NODE_deconvolution_scipy.egg-info/top_level.txt