Metadata-Version: 2.1
Name: NODE-deconvolution-scipy
Version: 0.1.3
Summary: A Python program for deconvolution spatial transcriptomics data and inference of spatial communication
Home-page: https://github.com/wzdrgi/NODE
Author: Zedong Wang
Author-email: wangzedong23@mails.ucas.ac.cn
License: MIT
Keywords: spatial transcriptomics,deconvolution ,spatial communication
Classifier: Development Status :: 3 - Alpha
Classifier: Intended Audience :: Developers
Classifier: Topic :: Software Development :: Build Tools
Classifier: License :: OSI Approved :: MIT License
Classifier: Programming Language :: Python :: 3
Classifier: Programming Language :: Python :: 3.4
Classifier: Programming Language :: Python :: 3.5
Classifier: Programming Language :: Python :: 3.6
Classifier: Programming Language :: Python :: 3.7
Classifier: Programming Language :: Python :: 3.8
Classifier: Programming Language :: Python :: 3.9
Classifier: Programming Language :: Python :: 3.10
Classifier: Programming Language :: Python :: 3.11
Classifier: Programming Language :: Python :: 3.12
